Metadata-Version: 1.1
Name: FrozenIdea
Version: 3.1.3
Summary: IRC bot toolkit.
Home-page: https://github.com/Bystroushaak/FrozenIdea
Author: Bystroushaak
Author-email: bystrousak@kitakitsune.org
License: MIT
Platform: UNKNOWN
Classifier: Development Status :: 4 - Beta
Classifier: Intended Audience :: Developers
Classifier: Programming Language :: Python
Classifier: Programming Language :: Python :: 3
Classifier: License :: OSI Approved :: MIT License
Classifier: Topic :: Communications
